leaderboards/__init__.py
leaderboards-0.0.0.dist-info/METADATA
leaderboards-0.0.0.dist-info/WHEEL
leaderboards-0.0.0.dist-info/top_level.txt
leaderboards-0.0.0.dist-info/RECORD
