Metadata-Version: 2.1
Name: leaderboards
Version: 0.0.0
Summary: Coming soon
Author-email: "Anastasios N. Angelopoulos" <angelopoulos@berkeley.edu>
